LICENSE.txt
MANIFEST.in
README.md
setup.cfg
setup.py
demo_tracify.egg-info/PKG-INFO
demo_tracify.egg-info/SOURCES.txt
demo_tracify.egg-info/dependency_links.txt
demo_tracify.egg-info/requires.txt
demo_tracify.egg-info/top_level.txt
requirements/base.txt
tracify/__init__.py
tracify/app_settings.py
tracify/apps.py
tracify/signals.py
tracify/utils.py
tracify/channels/__init__.py
tracify/channels/channel.py
tracify/channels/channels_factory.py
tracify/channels/backends/__init__.py
tracify/channels/backends/db.py
tracify/channels/backends/discord.py
tracify/channels/backends/email.py
tracify/channels/backends/slack.py
tracify/channels/backends/teams.py
tracify/db_backend/__init__.py
tracify/db_backend/admin.py
tracify/db_backend/apps.py
tracify/db_backend/models.py
tracify/db_backend/tests.py
tracify/db_backend/views.py
tracify/db_backend/migrations/0001_initial.py
tracify/db_backend/migrations/__init__.py
tracify/templates/issue_notifier.html
tracify/tests/__init__.py
tracify/tests/conftest.py
tracify/tests/test_channels_factory.py
tracify/tests/test_get_body_data.py
tracify/tests/channels/__init__.py
tracify/tests/channels/test_app_settings.py
tracify/tests/channels/test_channel.py
tracify/tests/channels/backends/__init__.py
tracify/tests/channels/backends/test_discord.py
tracify/tests/channels/backends/test_teams.py